pack_mm3_test/__init__.py
pack_mm3_test/rest_api.py
pack_mm3_test-0.0.5.dist-info/METADATA
pack_mm3_test-0.0.5.dist-info/WHEEL
pack_mm3_test-0.0.5.dist-info/top_level.txt
pack_mm3_test-0.0.5.dist-info/RECORD
